utils/__init__.py
utils/calculatrice.py
vwa_utils-1.0.dist-info/LICENCE.txt
vwa_utils-1.0.dist-info/METADATA
vwa_utils-1.0.dist-info/WHEEL
vwa_utils-1.0.dist-info/top_level.txt
vwa_utils-1.0.dist-info/RECORD
