Metadata-Version: 2.1
Name: vwa-utils
Version: 1.0
Summary: Test de PyTest
Author: Ecole IT
License-File: LICENCE.txt
